<?xml version="1.0" encoding="UTF-8"?>
<text xml:id="ParagnaLL3.1.1" status="created">  <!-- created, approved, updated--> <header>
        <creators>
            <creator>Porro</creator>
            <creator>Cantera</creator>
        </creators>
        <created/>
    </header>
    <div type="Stanza" sameAs="" n="1" xml:id="ParagnaLL3.1.1">
                
    </div>
    <Apparatus>
        <Critical/>
        <Commentary/>
    </Apparatus>
    <Parallels/>
    <Ritual>
        <Nerangs id="ritualNerangs">
            <ab>Neyrang-e hum čidan ParagnaLL3.1.1 (Mss. K36, 31):</ab>
            <ab class="ab_indent">
                nerang-e hum čidan be dastur-e barsom čidan vāǧ gereftan va be-hamān dastur čidan va se gereh-e hum aval ke be <em>ašem vohi</em> činad dar miyān-e angošt negāh dārid 
                va har čand ke ḫᵛāhad čidan va fe humdān kardan va be-hamān šāḫ be-dastur-e barsom čidan va vāǧ be-goftan ān se gereh-e hum rā ham be-humdān kardan va sar-e humdān 
                moḥkam kardan va dast az humdān ǧodā kardan va vāǧ tamām be goftan</ab>   
            <ab class="ab_indent">
                "Instruction for cutting the hum in the way as the cutting the <em>barsom</em>. He should take the <em>vāǧ</em> and cut it in the same way (like the <em>barsom</em>). 
                First, he cuts three pieces of <em>hum</em> (each one) while reciting one <em>Ašem Vohū</em>. You inspect them between your fingers. For as many as you want to cut 
                and put in the <em>humdān</em> he should say the <em>vāǧ</em> in the way as it is done for the cutting of the <em>barsom</em>. He should put these three pieces of 
                <em>hum</em> in the <em>humdān</em>, place the <em>humdān</em>, remove the hand from the <em>humdān</em> and complete the <em>vāǧ</em>."</ab>
        </Nerangs>
    </Ritual>
    <translation>
        <include type="CAB" corresp="CABTrParagnaLL3.1.1"/>
    </translation>
</text>