<?xml version="1.0" encoding="UTF-8"?>
<text xml:id="VrS2.25" status="created">  <!-- created, approved, updated--> <header>
        <creators>
            <creator>Porro</creator>
            <creator>Cantera</creator>
        </creators>
        <created>1 June 2019</created>
    </header>
    <div type="Stanza" sourceIs="Y2.15" xml:id="VrS2.25">
               <include href="/db/apps/cab_db/cab_rituals/static/Visperad_Static" xpointer="VrSY2.13"/>
            </div>
    <Speaker>
        <SpeakerInfo>
            <div>
                <ab class="ab_indent">zōt: 2109.</ab>
            </div>
        </SpeakerInfo>
        <Commentary/>
    </Speaker>
    <Apparatus>
        <Critical/>
        <Commentary/>
        <RecitationInstruction>
            <ab><em>aɱiia zaōϑre barəsmanaēca gairīm</em>] <em>ahmiia zaōϑre</em> (Per.) rāsfī ḫamuš <em>gairīm</em> 2109.</ab>
        </RecitationInstruction>
    </Apparatus>
    <Parallels/>
    <Ritual/>
    <translation>
        <include type="CAB" corresp="CABTrVrS2.25"/>
    </translation>
</text>