<?xml version="1.0" encoding="UTF-8"?>
<text xml:id="VrS4.27" status="created">
   <!-- created, approved, updated-->
   <header>
      <creators>
         <creator>Porro</creator>
         <creator>Cantera</creator>
      </creators>
      <created>1 June 2019</created>
   </header>
   <div type="Stanza" sourceIs="Y4.27" xml:id="VrS4.27">
      <include href="/db/apps/cab_db/cab_rituals/blocks/prayers/YeH" xpointer="YeH"/>
   </div>
   <Speaker>
      <SpeakerInfo>
         <div>
            <ab class="ab_indent">zōt: vid. VrS4.8, VrS4.17.</ab>
         </div>
      </SpeakerInfo>
      <Commentary/>
   </Speaker>
   <Apparatus>
      <Critical/>
      <Commentary/>
      <RecitationInstruction>
         <ab><em>yeŋ́hē hātąm</em> OD LOYŠE gwptn'] 2109; <em>yeŋ́hē hātąm</em> OD sʾl 2010; <em>yeŋ́hē hātąm</em> OD <em>tā̊scā yaz.</em> 2030; <em>yeŋ́hē hātąm</em> OD LOYŠE 2101. </ab>
      </RecitationInstruction>
   </Apparatus>
   <Parallels/>
   <Ritual/>
   <translation/>
</text>