<?xml version="1.0" encoding="UTF-8"?>
<text xml:id="VrS67.1" status="created">
   <!-- created, approved, updated-->
   <header>
      <creators>
         <creator>Porro</creator>
         <creator>Cantera</creator>
      </creators>
      <created>1 June 2019</created>
   </header>
   <div type="Stanza" sameAs="" xml:id="VrS67.1">
      <include href="/db/apps/cab_db/cab_rituals/blocks/prayers/YAV" xpointer="YAV1"/>
      <include href="/db/apps/cab_db/cab_rituals/blocks/prayers/YAV" xpointer="YAV"/>
   </div>
   <Apparatus>
      <Critical/>
      <Commentary/>
   </Apparatus>
   <Parallels/>
   <Ritual>
      <Nerangs id="ritualNerangs">
         <ab>VrS67.1 (mss. 2000, 2035, 2101):</ab>
         <ab class="ab_indent">
            <em>yaθā ahū vairiiō</em> dō guftan ‡ēč-at‡ anāstārīh ēn gyāg kunišn</ab> 
         <ab class="ab_indent">
            "They should recite two <em>yaθā ahū vairiiō</em> and make at this passage repentance of the sins."</ab>
      </Nerangs>
   </Ritual>
   <translation>
      <include type="CAB" corresp="CABTrVrS67.1"/>
   </translation>
</text>