<?xml version="1.0" encoding="UTF-8"?>
<text xml:id="VytVrS11.19" status="created">
   <!-- created, approved, updated-->
   <header>
      <creators>
         <creator>Porro</creator>
         <creator>Cantera</creator>
      </creators>
      <created>1 June 2019</created>
   </header>
   <div type="Stanza" sameAs="" xml:id="VytVrS11.19" quote="Y52.6">
      <include href="/db/apps/cab_db/cab_rituals/static/Vishtasp_Static" xpointer="VytSY11.12a"/>
      <include href="/db/apps/cab_db/cab_rituals/static/Vishtasp_Static" xpointer="VytSY11.12b"/>
      <include href="/db/apps/cab_db/cab_rituals/static/Vishtasp_Static" xpointer="VytSY11.12c"/>
   </div>
   <Speaker>
      <SpeakerInfo>
         <div>
            <ab class="ab_indent">zōt ud rāspīg: cf. VrS11.17.</ab>
         </div>
      </SpeakerInfo>
   </Speaker>
   <Apparatus>
      <Critical/>
      <Commentary/>
      <RecitationInstruction>
         <ab><em>vasasca tū...</em>] <em>vasasca tē ahura mazda uštāca xšaēša</em> OD <em>vīspaiiā̊ druuatō stōiš</em> (VytVrS10.22) 5020.</ab>
      </RecitationInstruction>
   </Apparatus>
   <Parallels/>
   <Ritual/>
   <translation>
      <include type="CAB" corresp="CABTrVytVrS11.19"/>
   </translation>
</text>