<?xml version="1.0" encoding="UTF-8"?>
<text xml:id="Y37.4" status="created">
   <!-- created, approved, updated-->
   <header>
      <creators>
         <creator>Porro</creator>
         <creator>Cantera</creator>
      </creators>
      <created>1 June 2019</created>
   </header>
   <div type="Stanza" sameAs="" xml:id="Y37.4">
      <include href="/db/apps/cab_db/cab_rituals/static/Yasna_static" xpointer="GY37.4"/>
   </div>
   <Apparatus>
      <Critical/>
      <Commentary/>
   </Apparatus>
   <Parallels>
      <ab>= Y5.4, VrS65.36.</ab>
   </Parallels>
   <Ritual/>
   <translation>
      <include type="CAB" corresp="CABTrY37.4"/>

        <include type="W" corresp="WTrY37.4"/>
        <include type="K" corresp="KTrY37.4"/>
        <include type="D" corresp="DTrY37.4"/>
    </translation>
</text>